cdhist/__init__.py
cdhist/__main__.py
cdhist/cdhist.py
cdhist/git_worktree.py
cdhist/utils.py
cdhist-4.4.dist-info/METADATA
cdhist-4.4.dist-info/WHEEL
cdhist-4.4.dist-info/entry_points.txt
cdhist-4.4.dist-info/top_level.txt
cdhist-4.4.dist-info/RECORD
