Metadata-Version: 2.4
Name: cdhist
Version: 4.4
Summary: Program to provide a Linux cd history directory stack
Author-email: Mark Blakeney <mark.blakeney@bullet-systems.net>
License-Expression: GPL-3.0-or-later
Project-URL: Homepage, https://github.com/bulletmark/cdhist
Keywords: bash,zsh,cd,fzf,git,worktree
Classifier: Programming Language :: Python :: 3
Requires-Python: >=3.8
